bosch_thermostat_client/__init__.py
bosch_thermostat_client/bosch_cli.py
bosch_thermostat_client/bosch_examples.py
bosch_thermostat_client/circuits/__init__.py
bosch_thermostat_client/circuits/circuit.py
bosch_thermostat_client/circuits/circuits.py
bosch_thermostat_client/circuits/easycontrol/__init__.py
bosch_thermostat_client/circuits/easycontrol/base.py
bosch_thermostat_client/circuits/easycontrol/dhw.py
bosch_thermostat_client/circuits/easycontrol/zone.py
bosch_thermostat_client/circuits/ivt/__init__.py
bosch_thermostat_client/circuits/ivt/base.py
bosch_thermostat_client/circuits/nefit/__init__.py
bosch_thermostat_client/circuits/nefit/base.py
bosch_thermostat_client/circuits/nefit/heating.py
bosch_thermostat_client/connectors/__init__.py
bosch_thermostat_client/connectors/client/slixmpp.py
bosch_thermostat_client/connectors/client/slixmpp010.py
bosch_thermostat_client/connectors/easycontrol.py
bosch_thermostat_client/connectors/http.py
bosch_thermostat_client/connectors/ivt.py
bosch_thermostat_client/connectors/nefit.py
bosch_thermostat_client/connectors/xmpp.py
bosch_thermostat_client/const/__init__.py
bosch_thermostat_client/const/easycontrol.py
bosch_thermostat_client/const/ivt.py
bosch_thermostat_client/const/nefit.py
bosch_thermostat_client/db/__init__.py
bosch_thermostat_client/db/can/010602.json
bosch_thermostat_client/db/can/010701.json
bosch_thermostat_client/db/db_EASYCONTROL.json
bosch_thermostat_client/db/db_IVT.json
bosch_thermostat_client/db/db_IVT_MBLAN.json
bosch_thermostat_client/db/db_NEFIT.json
bosch_thermostat_client/db/default/011003.json
bosch_thermostat_client/db/easycontrol/030401.json
bosch_thermostat_client/db/easycontrol/030602.json
bosch_thermostat_client/db/easycontrol/030603.json
bosch_thermostat_client/db/easycontrol/030605.json
bosch_thermostat_client/db/easycontrol/030801.json
bosch_thermostat_client/db/easycontrol/031000.json
bosch_thermostat_client/db/easycontrol/031200.json
bosch_thermostat_client/db/easycontrol/031302.json
bosch_thermostat_client-0.28.2.dist-info/entry_points.txt
bosch_thermostat_client-0.28.2.dist-info/WHEEL
bosch_thermostat_client-0.28.2.dist-info/METADATA
bosch_thermostat_client-0.28.2.dist-info/licenses/LICENSE.txt
bosch_thermostat_client-0.28.2.dist-info/RECORD
