Metadata-Version: 2.1
Name: bosch-thermostat-client
Version: 0.28.2
Summary: Python API for talking to Bosch™ Heating gateway using HTTP or XMPP
License: Apache License 2.0
Author-email: Pawel Szafer <pszafer@gmail.com>
Requires-Python: >=3.12
Requires-Dist: aiohttp>=3.9.0
Requires-Dist: click>=8.1.7
Requires-Dist: colorlog>=6.8.2
Requires-Dist: pyaes>=1.6.1
Requires-Dist: pytz>=2024.1
Requires-Dist: pyyaml>=6.0.1
Requires-Dist: slixmpp>=1.8.5
